test65452345785324.py
test65452345785324-0.0.8.dist-info/WHEEL
test65452345785324-0.0.8.dist-info/METADATA
test65452345785324-0.0.8.dist-info/RECORD
