Metadata-Version: 2.4
Name: test65452345785324
Version: 0.0.8
Summary: descriptione here
Requires-Python: >=3.7
License-Expression: 0BSD
Project-URL: Documentation, https://github.com/0b-0/test/blob/main/test65452345785324.py
